README
fablib.py
setup.py
fablib.egg-info/PKG-INFO
fablib.egg-info/SOURCES.txt
fablib.egg-info/dependency_links.txt
fablib.egg-info/top_level.txt