Metadata-Version: 1.1
Name: fablib
Version: 0.1.0
Summary: Fabric deployment helper functions
Home-page: http://github.com/gpoulter/fablib
Author: Graham Poulter
Author-email: graham.poulter@gmail.com
License: MIT
Platform: UNKNOWN
Classifier: Development Status :: 3 - Alpha
Classifier: Intended Audience :: Developers
Classifier: License :: OSI Approved :: MIT License
Classifier: Topic :: Software Development :: Build Tools
Classifier: Topic :: System :: Installation/Setup
Classifier: Operating System :: OS Independent
Classifier: Programming Language :: Python
Classifier: Programming Language :: Python :: 2
Classifier: Programming Language :: Python :: 2.7
